checksum/__init__.py
checksum-1.0.4.dist-info/DESCRIPTION.rst
checksum-1.0.4.dist-info/METADATA
checksum-1.0.4.dist-info/RECORD
checksum-1.0.4.dist-info/WHEEL
checksum-1.0.4.dist-info/metadata.json
checksum-1.0.4.dist-info/top_level.txt
